animeplanet/__init__.py
animeplanet/animeplanet.py
animeplanet-0.1.0.dist-info/DESCRIPTION.rst
animeplanet-0.1.0.dist-info/METADATA
animeplanet-0.1.0.dist-info/RECORD
animeplanet-0.1.0.dist-info/WHEEL
animeplanet-0.1.0.dist-info/entry_points.txt
animeplanet-0.1.0.dist-info/metadata.json
animeplanet-0.1.0.dist-info/top_level.txt
