Metadata-Version: 2.0
Name: animeplanet
Version: 0.1.0
Summary: Python Module for Interacting with Anime Planet
Home-page: https://github.com/radomirbosak/animeplanet
Author: Radomír Bosák
Author-email: radomir.bosak@gmail.com
License: MIT
Keywords: animeplanet,anime,cli
Platform: UNKNOWN
Classifier: License :: OSI Approved :: MIT License
Classifier: Operating System :: OS Independent
Classifier: Programming Language :: Python
Classifier: Programming Language :: Python :: 3
Classifier: Programming Language :: Python :: 3.3
Classifier: Programming Language :: Python :: 3.4
Classifier: Programming Language :: Python :: 3.5
Classifier: Programming Language :: Python :: 3.6
Classifier: Programming Language :: Python :: 3.7
Requires-Dist: requests-html
